Workbook

Sheet 01_组合概览
A1: 📊 投资组合跟踪仪表盘
A3: 指标名称 | B3: 数值 | C3: 说明
A4: 组合总市值 | B4: ¥100,000 | C4: 当前持仓总市值
A5: 当日盈亏 | B5: ¥0 | C5: 当日浮动盈亏
A6: 累计收益率 | B6: 0.00% | C6: 相对于初始本金
A7: 年化收益率 | B7: 0.00% | C7: 年化计算
A8: 最大回撤 | B8: 0.00% | C8: 历史最大回撤
A9: 夏普比率 | B9: 0.00 | C9: 风险调整后收益
A10: 持仓数量 | B10: 18只 | C10: 当前持仓标的数
A11: 现金比例 | B11: 3.00% | C11: 现金占总资产比例
A14: 📈 板块配置分布 | E14: ⚠️ 预警信号
A15: 板块 | B15: 目标市值 | C15: 占比 | E15: 预警类型 | F15: 触发条件 | G15: 当前状态
A16: 上游油气 | B16: ¥18,000 | C16: 13.1% | E16: 止损预警 | F16: 股价<止损价 | G16: 正常
A17: LNG | B17: ¥12,000 | C17: 8.8% | E17: 目标价预警 | F17: 股价>目标价 95% | G17: 正常
A18: 油服 | B18: ¥12,000 | C18: 8.8% | E18: 权重偏离 | F18: 偏离>15% | G18: 正常
A19: 煤炭化工 | B19: ¥12,000 | C19: 8.8% | E19: 股息率达标 | F19: 股息率>3% | G19: 部分达标
A20: 特高压 | B20: ¥18,000 | C20: 13.1% | E20: 估值分位 | F20: PE 分位<30% | G20: 合理
A21: 新能源 | B21: ¥20,000 | C21: 14.6%
A22: 黄金 | B22: ¥18,000 | C22: 13.1%
A23: 军工 | B23: ¥15,000 | C23: 10.9%
A24: 政策方向 | B24: ¥12,000 | C24: 8.8%

Sheet 07_参数设置
A1: 全局参数设置
A2: 参数名称 | B2: 当前值 | C2: 说明
A3: 初始本金 | B3: 100000 | C3: 组合起始资金（元）
A4: 无风险利率 | B4: 0.025 | C4: 用于夏普比率计算（年化 2.5%）
A5: 交易佣金率 | B5: 0.00025 | C5: 买入佣金 0.025%
A6: 印花税率 | B6: 0.001 | C6: 卖出印花税 0.1%
A7: 再平衡阈值 | B7: 0.15 | C7: 权重偏离超过 15% 触发再平衡
A8: 止损阈值 | B8: -0.15 | C8: 单标的亏损 15% 触发止损检查
A9: 数据更新日 | B9: 2026-03-20 | C9: 最后更新时间
A11: 18 只标的策略参数表
A12: 代码 | B12: 名称 | C12: 板块 | D12: 目标仓位% | E12: 入场下限 | F12: 入场上限 | G12: 止损价 | H12: 目标价 | I12: 仓位上限% | J12: 股息率% | K12: PE(TTM) | L12: 检视频率
A13: 600938 | B13: 中国海油 | C13: 上游油气 | D13: 10 | E13: 38.5 | F13: 40.5 | G13: 36 | H13: 52 | I13: 12 | J13: 5.2 | K13: 14.4 | L13: 月度
A14: 601857 | B14: 中国石油 | C14: 上游油气 | D14: 8 | E14: 11.8 | F14: 12.8 | G14: 10.8 | H14: 16 | I14: 10 | J14: 4.3 | K14: 13.2 | L14: 月度
A15: 600256 | B15: 广汇能源 | C15: LNG | D15: 6 | E15: 6.2 | F15: 7.2 | G15: 5.5 | H15: 10 | I15: 8 | J15: 3.5 | K15: 33.1 | L15: 月度
A16: 600803 | B16: 新奥股份 | C16: LNG | D16: 6 | E16: 19.5 | F16: 22.5 | G16: 18 | H16: 28 | I16: 8 | J16: 3 | K16: 13.7 | L16: 月度
A17: 601808 | B17: 中海油服 | C17: 油服 | D17: 6 | E17: 16.5 | F17: 18 | G17: 15 | H17: 23 | I17: 8 | J17: 2.1 | K17: 19.4 | L17: 月度
A18: 002353 | B18: 杰瑞股份 | C18: 油服 | D18: 6 | E18: 90 | F18: 100 | G18: 85 | H18: 125 | I18: 10 | J18: 0.9 | K18: 36.1 | L18: 月度
A19: 601088 | B19: 中国神华 | C19: 煤炭化工 | D19: 8 | E19: 43 | F19: 47 | G19: 40 | H19: 55 | I19: 10 | J19: 7 | K19: 13 | L19: 月度
A20: 600426 | B20: 华鲁恒升 | C20: 煤炭化工 | D20: 4 | E20: 36 | F20: 41 | G20: 33 | H20: 48 | I20: 8 | J20: 2.5 | K20: 20 | L20: 月度
A21: 600406 | B21: 国电南瑞 | C21: 特高压 | D21: 12 | E21: 29 | F21: 31.5 | G21: 27 | H21: 40 | I21: 15 | J21: 2 | K21: 25 | L21: 月度
A22: 000400 | B22: 许继电气 | C22: 特高压 | D22: 6 | E22: 31 | F22: 35 | G22: 28 | H22: 43 | I22: 8 | J22: 1.5 | K22: 30 | L22: 月度
A23: 300750 | B23: 宁德时代 | C23: 新能源 | D23: 12 | E23: 380 | F23: 410 | G23: 360 | H23: 500 | I23: 12 | J23: 1 | K23: 28 | L23: 月度
A24: 300274 | B24: 阳光电源 | C24: 新能源 | D24: 8 | E24: 155 | F24: 170 | G24: 145 | H24: 210 | I24: 12 | J24: 1.2 | K24: 22 | L24: 月度
... A30: 600536 | B30: 中国软件 | C30: 政策方向 | D30: 4 | E30: 42 | F30: 48 | G30: 38 | H30: 60 | I30: 8 | J30: 0.5 | K30: 80 | L30: 月度

Sheet 02_持仓明细
A1: 股票代码 | B1: 股票名称 | C1: 所属板块 | D1: 目标仓位% | E1: 持仓数量 | F1: 持仓成本 | G1: 当前股价 | H1: 持仓市值 | I1: 实际仓位% | J1: 浮动盈亏 | K1: 盈亏比例% | L1: 入场下限 | M1: 入场上限 | N1: 止损价 | O1: 目标价 | P1: 股息率% | Q1: PE(TTM) | R1: 技术信号 | S1: 基本面评级 | T1: 操作建议 | U1: 备注
A2: 600938 | B2: 中国海油 | C2: 上游油气 | D2: 10 | E2: 0 | F2: 0 | G2: 42.24 | H2: =E2*G2 | I2: =H2/'01 组合概览'!$B$2 | J2: =(G2-F2)*E2 | K2: =(G2-F2)/F2 | L2: 38.5 | M2: 40.5 | N2: 36 | O2: 52 | P2: 5.2 | Q2: 14.4 | R2: 观望 | S2: 良好 | T2: 持有
A3: 601857 | B3: 中国石油 | C3: 上游油气 | D3: 8 | E3: 0 | F3: 0 | G3: 12.5 | H3: =E3*G3 | I3: =H3/'01 组合概览'!$B$2 | J3: =(G3-F3)*E3 | K3: =(G3-F3)/F3 | L3: 11.8 | M3: 12.8 | N3: 10.8 | O3: 16 | P3: 4.3 | Q3: 13.2 | R3: 观望 | S3: 良好 | T3: 持有
A4: 600256 | B4: 广汇能源 | C4: LNG | D4: 6 | E4: 0 | F4: 0 | G4: 7 | H4: =E4*G4 | I4: =H4/'01 组合概览'!$B$2 | J4: =(G4-F4)*E4 | K4: =(G4-F4)/F4 | L4: 6.2 | M4: 7.2 | N4: 5.5 | O4: 10 | P4: 3.5 | Q4: 33.1 | R4: 观望 | S4: 良好 | T4: 持有
A5: 600803 | B5: 新奥股份 | C5: LNG | D5: 6 | E5: 0 | F5: 0 | G5: 22 | H5: =E5*G5 | I5: =H5/'01 组合概览'!$B$2 | J5: =(G5-F5)*E5 | K5: =(G5-F5)/F5 | L5: 19.5 | M5: 22.5 | N5: 18 | O5: 28 | P5: 3 | Q5: 13.7 | R5: 观望 | S5: 良好 | T5: 持有
A6: 601808 | B6: 中海油服 | C6: 油服 | D6: 6 | E6: 0 | F6: 0 | G6: 17.4 | H6: =E6*G6 | I6: =H6/'01 组合概览'!$B$2 | J6: =(G6-F6)*E6 | K6: =(G6-F6)/F6 | L6: 16.5 | M6: 18 | N6: 15 | O6: 23 | P6: 2.1 | Q6: 19.4 | R6: 观望 | S6: 良好 | T6: 持有
A7: 002353 | B7: 杰瑞股份 | C7: 油服 | D7: 6 | E7: 0 | F7: 0 | G7: 99 | H7: =E7*G7 | I7: =H7/'01 组合概览'!$B$2 | J7: =(G7-F7)*E7 | K7: =(G7-F7)/F7 | L7: 90 | M7: 100 | N7: 85 | O7: 125 | P7: 0.9 | Q7: 36.1 | R7: 观望 | S7: 良好 | T7: 持有
A8: 601088 | B8: 中国神华 | C8: 煤炭化工 | D8: 8 | E8: 0 | F8: 0 | G8: 46 | H8: =E8*G8 | I8: =H8/'01 组合概览'!$B$2 | J8: =(G8-F8)*E8 | K8: =(G8-F8)/F8 | L8: 43 | M8: 47 | N8: 40 | O8: 55 | P8: 7 | Q8: 13 | R8: 观望 | S8: 良好 | T8: 持有
A9: 600426 | B9: 华鲁恒升 | C9: 煤炭化工 | D9: 4 | E9: 0 | F9: 0 | G9: 35.6 | H9: =E9*G9 | I9: =H9/'01 组合概览'!$B$2 | J9: =(G9-F9)*E9 | K9: =(G9-F9)/F9 | L9: 36 | M9: 41 | N9: 33 | O9: 48 | P9: 2.5 | Q9: 20 | R9: 观望 | S9: 良好 | T9: 持有
A10: 600406 | B10: 国电南瑞 | C10: 特高压 | D10: 12 | E10: 0 | F10: 0 | G10: 30.7 | H10: =E10*G10 | I10: =H10/'01 组合概览'!$B$2 | J10: =(G10-F10)*E10 | K10: =(G10-F10)/F10 | L10: 29 | M10: 31.5 | N10: 27 | O10: 40 | P10: 2 | Q10: 25 | R10: 观望 | S10: 良好 | T10: 持有
A11: 000400 | B11: 许继电气 | C11: 特高压 | D11: 6 | E11: 0 | F11: 0 | G11: 33.6 | H11: =E11*G11 | I11: =H11/'01 组合概览'!$B$2 | J11: =(G11-F11)*E11 | K11: =(G11-F11)/F11 | L11: 31 | M11: 35 | N11: 28 | O11: 43 | P11: 1.5 | Q11: 30 | R11: 观望 | S11: 良好 | T11: 持有
A12: 300750 | B12: 宁德时代 | C12: 新能源 | D12: 12 | E12: 0 | F12: 0 | G12: 400.5 | H12: =E12*G12 | I12: =H12/'01 组合概览'!$B$2 | J12: =(G12-F12)*E12 | K12: =(G12-F12)/F12 | L12: 380 | M12: 410 | N12: 360 | O12: 500 | P12: 1 | Q12: 28 | R12: 观望 | S12: 良好 | T12: 持有
A13: 300274 | B13: 阳光电源 | C13: 新能源 | D13: 8 | E13: 0 | F13: 0 | G13: 165.1 | H13: =E13*G13 | I13: =H13/'01 组合概览'!$B$2 | J13: =(G13-F13)*E13 | K13: =(G13-F13)/F13 | L13: 155 | M13: 170 | N13: 145 | O13: 210 | P13: 1.2 | Q13: 22 | R13: 观望 | S13: 良好 | T13: 持有
... A19: 600536 | B19: 中国软件 | C19: 政策方向 | D19: 4 | E19: 0 | F19: 0 | G19: 45 | H19: =E19*G19 | I19: =H19/'01 组合概览'!$B$2 | J19: =(G19-F19)*E19 | K19: =(G19-F19)/F19 | L19: 42 | M19: 48 | N19: 38 | O19: 60 | P19: 0.5 | Q19: 80 | R19: 观望 | S19: 良好 | T19: 持有

Sheet 03_交易记录
A1: 交易日期 | B1: 股票代码 | C1: 股票名称 | D1: 交易类型 | E1: 交易价格 | F1: 交易数量 | G1: 交易金额 | H1: 手续费 | I1: 净现金流 | J1: 交易后持仓 | K1: 交易后成本 | L1: 交易理由 | M1: 操作人 | N1: 备注
A2: 2026-03-20 | B2: 600938 | C2: 中国海油 | D2: 买入 | E2: 40 | F2: 1000 | G2: 40000 | H2: 100 | I2: -40100 | J2: 1000 | K2: 40 | L2: 回调至支撑位建仓 | M2: 用户 | N2: 首仓

Sheet 04_财务监控
A1: 股票代码 | B1: 股票名称 | C1: 报告期 | D1: 营收 (亿) | E1: 营收同比% | F1: 净利润 (亿) | G1: 净利润同比% | H1: 毛利率% | I1: ROE% | J1: 负债率% | K1: 经营现金流 (亿) | L1: 数据来源 | M1: 更新日期
A2: 600938 | B2: 中国海油 | C2: 2026Q1 | D2: 0 | E2: 0 | F2: 0 | G2: 0 | H2: 0 | I2: 0 | J2: 0 | K2: 0 | L2: 待更新 | M2: 2026-03-20
A3: 600938 | B3: 中国海油 | C3: 2025Q4 | D3: 0 | E3: 0 | F3: 0 | G3: 0 | H3: 0 | I3: 0 | J3: 0 | K3: 0 | L3: 待更新 | M3: 2026-03-20
A4: 601857 | B4: 中国石油 | C4: 2026Q1 | D4: 0 | E4: 0 | F4: 0 | G4: 0 | H4: 0 | I4: 0 | J4: 0 | K4: 0 | L4: 待更新 | M4: 2026-03-20
A5: 601857 | B5: 中国石油 | C5: 2025Q4 | D5: 0 | E5: 0 | F5: 0 | G5: 0 | H5: 0 | I5: 0 | J5: 0 | K5: 0 | L5: 待更新 | M5: 2026-03-20
A6: 600256 | B6: 广汇能源 | C6: 2026Q1 | D6: 0 | E6: 0 | F6: 0 | G6: 0 | H6: 0 | I6: 0 | J6: 0 | K6: 0 | L6: 待更新 | M6: 2026-03-20
A7: 600256 | B7: 广汇能源 | C7: 2025Q4 | D7: 0 | E7: 0 | F7: 0 | G7: 0 | H7: 0 | I7: 0 | J7: 0 | K7: 0 | L7: 待更新 | M7: 2026-03-20
A8: 600803 | B8: 新奥股份 | C8: 2026Q1 | D8: 0 | E8: 0 | F8: 0 | G8: 0 | H8: 0 | I8: 0 | J8: 0 | K8: 0 | L8: 待更新 | M8: 2026-03-20
A9: 600803 | B9: 新奥股份 | C9: 2025Q4 | D9: 0 | E9: 0 | F9: 0 | G9: 0 | H9: 0 | I9: 0 | J9: 0 | K9: 0 | L9: 待更新 | M9: 2026-03-20
A10: 601808 | B10: 中海油服 | C10: 2026Q1 | D10: 0 | E10: 0 | F10: 0 | G10: 0 | H10: 0 | I10: 0 | J10: 0 | K10: 0 | L10: 待更新 | M10: 2026-03-20
A11: 601808 | B11: 中海油服 | C11: 2025Q4 | D11: 0 | E11: 0 | F11: 0 | G11: 0 | H11: 0 | I11: 0 | J11: 0 | K11: 0 | L11: 待更新 | M11: 2026-03-20

Sheet 05_技术信号
A1: 股票代码 | B1: 股票名称 | C1: 更新日期 | D1: 收盘价 | E1: 5 日均线 | F1: 20 日均线 | G1: 60 日均线 | H1: MACD | I1: RSI(14) | J1: 成交量 (万手) | K1: 技术形态 | L1: 关键支撑 | M1: 关键阻力 | N1: 信号建议
A2: 600938 | B2: 中国海油 | C2: 2026-03-20 | D2: 42.24 | E2: 0 | F2: 0 | G2: 0 | H2: 0 | I2: 50 | J2: 0 | K2: 震荡 | L2: 38.5 | M2: 40.5 | N2: 持有
A3: 601857 | B3: 中国石油 | C3: 2026-03-20 | D3: 12.5 | E3: 0 | F3: 0 | G3: 0 | H3: 0 | I3: 50 | J3: 0 | K3: 震荡 | L3: 11.8 | M3: 12.8 | N3: 持有
A4: 600256 | B4: 广汇能源 | C4: 2026-03-20 | D4: 7 | E4: 0 | F4: 0 | G4: 0 | H4: 0 | I4: 50 | J4: 0 | K4: 震荡 | L4: 6.2 | M4: 7.2 | N4: 持有
A5: 600803 | B5: 新奥股份 | C5: 2026-03-20 | D5: 22 | E5: 0 | F5: 0 | G5: 0 | H5: 0 | I5: 50 | J5: 0 | K5: 震荡 | L5: 19.5 | M5: 22.5 | N5: 持有
A6: 601808 | B6: 中海油服 | C6: 2026-03-20 | D6: 17.4 | E6: 0 | F6: 0 | G6: 0 | H6: 0 | I6: 50 | J6: 0 | K6: 震荡 | L6: 16.5 | M6: 18 | N6: 持有
A7: 002353 | B7: 杰瑞股份 | C7: 2026-03-20 | D7: 99 | E7: 0 | F7: 0 | G7: 0 | H7: 0 | I7: 50 | J7: 0 | K7: 震荡 | L7: 90 | M7: 100 | N7: 持有
A8: 601088 | B8: 中国神华 | C8: 2026-03-20 | D8: 46 | E8: 0 | F8: 0 | G8: 0 | H8: 0 | I8: 50 | J8: 0 | K8: 震荡 | L8: 43 | M8: 47 | N8: 持有
A9: 600426 | B9: 华鲁恒升 | C9: 2026-03-20 | D9: 35.6 | E9: 0 | F9: 0 | G9: 0 | H9: 0 | I9: 50 | J9: 0 | K9: 震荡 | L9: 36 | M9: 41 | N9: 持有
A10: 600406 | B10: 国电南瑞 | C10: 2026-03-20 | D10: 30.7 | E10: 0 | F10: 0 | G10: 0 | H10: 0 | I10: 50 | J10: 0 | K10: 震荡 | L10: 29 | M10: 31.5 | N10: 持有
A11: 000400 | B11: 许继电气 | C11: 2026-03-20 | D11: 33.6 | E11: 0 | F11: 0 | G11: 0 | H11: 0 | I11: 50 | J11: 0 | K11: 震荡 | L11: 31 | M11: 35 | N11: 持有
A12: 300750 | B12: 宁德时代 | C12: 2026-03-20 | D12: 400.5 | E12: 0 | F12: 0 | G12: 0 | H12: 0 | I12: 50 | J12: 0 | K12: 震荡 | L12: 380 | M12: 410 | N12: 持有
A13: 300274 | B13: 阳光电源 | C13: 2026-03-20 | D13: 165.1 | E13: 0 | F13: 0 | G13: 0 | H13: 0 | I13: 50 | J13: 0 | K13: 震荡 | L13: 155 | M13: 170 | N13: 持有
... A19: 600536 | B19: 中国软件 | C19: 2026-03-20 | D19: 45 | E19: 0 | F19: 0 | G19: 0 | H19: 0 | I19: 50 | J19: 0 | K19: 震荡 | L19: 42 | M19: 48 | N19: 持有

Sheet 06_再平衡日志
A1: 检视日期 | B1: 触发原因 | C1: 调整标的 | D1: 调整前仓位% | E1: 目标仓位% | F1: 调整后仓位% | G1: 操作动作 | H1: 交易金额 | I1: 调整后组合收益 | J1: 备注
A2: 2026-03-20 | B2: 月度检视 | C2: 中国海油 | D2: 13.5 | E2: 10 | F2: 10.2 | G2: 减仓 3.3% | H2: -32000 | I2: 8.35% | J2: 油价冲高止盈部分
A3: 2026-03-20 | B3: 月度检视 | C3: 阳光电源 | D3: 6.8 | E3: 8 | F3: 7.9 | G3: 加仓 1.1% | H3: 11000 | I3: 8.35% | J3: 回调至支撑位加仓
